exoskeleton/__init__.py
exoskeleton/__main__.py
exoskeleton/_version.py
exoskeleton/actions.py
exoskeleton/blocklist_manager.py
exoskeleton/database_connection.py
exoskeleton/database_schema_check.py
exoskeleton/err.py
exoskeleton/error_manager.py
exoskeleton/exo_url.py
exoskeleton/file_manager.py
exoskeleton/helpers.py
exoskeleton/job_manager.py
exoskeleton/label_manager.py
exoskeleton/notification_manager.py
exoskeleton/py.typed
exoskeleton/queue_manager.py
exoskeleton/remote_control_chrome.py
exoskeleton/statistics_manager.py
exoskeleton/time_manager.py
exoskeleton-2.1.1.dist-info/LICENSE
exoskeleton-2.1.1.dist-info/METADATA
exoskeleton-2.1.1.dist-info/WHEEL
exoskeleton-2.1.1.dist-info/top_level.txt
exoskeleton-2.1.1.dist-info/RECORD
