Metadata-Version: 2.1
Name: exoskeleton
Version: 2.1.1
Summary: A library to create a bot / spider / crawler.
Home-page: https://github.com/RuedigerVoigt/exoskeleton
Author: Rüdiger Voigt
Author-email: projects@ruediger-voigt.eu
License: UNKNOWN
Platform: UNKNOWN
Classifier: Programming Language :: Python :: 3
Classifier: Programming Language :: Python :: 3.8
Classifier: Programming Language :: Python :: 3.9
Classifier: Programming Language :: Python :: 3.10
Classifier: License :: OSI Approved :: Apache Software License
Classifier: Operating System :: OS Independent
Classifier: Development Status :: 5 - Production/Stable
Classifier: Intended Audience :: Science/Research
Classifier: Intended Audience :: Developers
Classifier: Topic :: Text Processing :: Markup :: HTML
Classifier: Topic :: Internet :: WWW/HTTP :: Indexing/Search
Requires-Python: >=3.8
Requires-Dist: aiodns (>=3.0.0)
Requires-Dist: aiohttp (>=3.8.1)
Requires-Dist: beautifulsoup4 (>=4.11.1)
Requires-Dist: bote (>=1.2.2)
Requires-Dist: chardet (>=4.0.0)
Requires-Dist: compatibility (>=1.0.1)
Requires-Dist: lxml (>=4.8.0)
Requires-Dist: pycares (>=4.1.2)
Requires-Dist: pymysql (>=1.0.2)
Requires-Dist: requests (>=2.27.1)
Requires-Dist: urllib3 (>=1.26.9)
Requires-Dist: userprovided (>=0.9.4)
